kubeml/__init__.py
kubeml/dataset.py
kubeml/exceptions.py
kubeml/hooks.py
kubeml/network.py
kubeml/util.py
kubeml-0.1.7.dist-info/LICENSE
kubeml-0.1.7.dist-info/METADATA
kubeml-0.1.7.dist-info/WHEEL
kubeml-0.1.7.dist-info/top_level.txt
kubeml-0.1.7.dist-info/RECORD
