Metadata-Version: 2.1
Name: kubeml
Version: 0.1.7
Summary: Python tools for training Neural Networks with KubeML
Home-page: UNKNOWN
Author: Diego Albo Martínez
Author-email: diego.albo.martinez@gmail.com
License: MIT
Platform: UNKNOWN
Requires-Dist: torch (>=1.7)
Requires-Dist: redisai (>=1.0.1)
Requires-Dist: pymongo (>=3.11.1)
Requires-Dist: flask (>=1.1.2)
